{
    "trachian": {
        "type": "simple",
        "male": [
            "Vilip",
            "Raeczanter",
            "Juliuz",
            "Līvhart",
            "Hellīvīlacht",
            "Natrēaz",
            "Cideon",
            "Vuttūvert",
            "Ingcīnālu",
            "Criztof",
            "Attālar",
            "Ingccurf",
            "Liuthhīli",
            "Hartvvīlacht",
            "Vittīcint",
            "Nanncavrat",
            "Cizzrahīli",
            "Cangvvurf",
            "Hillīvīc",
            "Johnaiz",
            "Natēoz",
            "Narcoz",
            "Lucaz",
            "Jacūvoz",
            "Petroz",
            "Paloz",
            "Tunaz",
            "Ztefnaoz",
            "Uottrāīchi",
            "Cirvvīn",
            "Ritvvīc",
            "Arprrīchi",
            "Manfrīti",
            "Atan",
            "Jonaz",
            "Paner",
            "Zinzon",
            "Zeburon",
            "Erīaz",
            "Jotān",
            "Aznuēr",
            "Ruvan"
        ],
        "female": [
            "Āocozta",
            "Cālolina",
            "Arnnīhirtja",
            "Heirccart",
            "Liuvttruot",
            "Hirttjālīn",
            "Cizzrahīla",
            "Uottrāīcha",
            "Cirvvīna",
            "Ritvvīca",
            "Arprrīcha",
            "Naeni"
        ]
    },
    "xoteohl": {
        "type": "simple",
        "male": [
            "Ahuoxohl",
            "Milinitica",
            "Eacahl",
            "Xolin",
            "Tacelel",
            "Oamac",
            "Xuocoxuo",
            "Texin",
            "Texicoehua",
            "Coxamapan",
            "Micahlanetequihli",
            "Taxoahlaleni",
            "Nexahualocuotuohl",
            "Xicuoetenacahl",
            "Xiocoahl",
            "Texoxemoc"
        ],
        "female": [
            "Ixel",
            "Tuolihli",
            "Ciahuoxuoxihl",
            "Xuoco",
            "Coxacahl",
            "Accatuohl",
            "Eocotuohl",
            "Maxata",
            "Motuelehla",
            "Toletecapilli",
            "Ihuacahl",
            "Ihuihl",
            "Tepin"
        ]
    },
    "selean": {
        "type": "simple",
        "male": [
            "Petrich",
            "Merevith",
            "Rêthver",
            "Vilhel",
            "Egelvin",
            "Vigot",
            "Elrêt",
            "Farman",
            "Thêdver",
            "Nîgûl",
            "Felgil",
            "Edhelrîh",
            "Sasvul",
            "Fridheghodh",
            "Ermenrêdh",
            "Vulhadh",
            "Cêlvar",
            "Êrîh"
        ],
        "female": [
            "Gênvur",
            "Cynevur"
        ]
    },
    "trinosian": {
        "type": "simple",
        "male": [
            "Euzîn",
            "Crîztîani",
            "Cêrl",
            "Êrêrd",
            "Êrezt",
            "Nîgûla",
            "Zazûnî",
            "Zuzt",
            "Dzeronz",
            "Pompûniu",
            "Vodin",
            "Iscirione"
        ],
        "female": [
            "Zaena"
        ]
    },
    "prad": {
        "type": "simple",
        "male": [
            "Arcos",
            "Anchas",
            "Jufys",
            "Anois",
            "Teomes",
            "Vusants",
            "Ampals",
            "Natreas",
            "Atan",
            "Atans",
            "Jonas",
            "Paner",
            "Paners",
            "Zinzons",
            "Zinzon",
            "Zebulon",
            "Zebulons",
            "Elias",
            "Jotan",
            "Jotans",
            "Aznuer",
            "Aznuers",
            "Luvan",
            "Luvans"
        ],
        "female": [
            "Arcog",
            "Anchag",
            "Jufyg",
            "Anoig",
            "Teomeg",
            "Vusant",
            "Ampalg",
            "Naeni",
            "Naenig"
        ]
    },
    "felgriftian": {
        "type": "simple",
        "male": [
            "Ioen",
            "Iog",
            "Amonual",
            "Osav",
            "Esoc",
            "Barnova",
            "Ilon",
            "Diog",
            "Astevon",
            "Modios",
            "Fovion",
            "Neolos",
            "Xova",
            "Mocsemelion",
            "Ovrom",
            "Ion",
            "Pol",
            "Esoios",
            "Morise",
            "Olagsonra",
            "Gellalm",
            "Rofoal",
            "Rolon",
            "Llaonor"
        ]
    },
    "luonkuenese": {
        "type": "composite",
        "surname": [
            "Dwe (屠)",
            "Xwé (懷)",
            "Xxwet (闕)",
            "Kkwok (國)",
            "Kkun (公)",
            "Súkk (宿)",
            "Kkwan (關)",
            "Dén (陳)"
        ],
        "male": [
            "Bóxó (抱豪)",
            "Sidó (子道)",
            "Wen'ek (永一)",
            "Wezé (睿才)",
            "Ékxakk (燁赫)",
            "Xunshé (鴻彩)",
            "Kweho (飛虎)"
        ],
        "female": []
    }
}